ysfitsutilpy/__init__.py
ysfitsutilpy/airmass.py
ysfitsutilpy/astroim.py
ysfitsutilpy/astrometry.py
ysfitsutilpy/combutil.py
ysfitsutilpy/filemgmt.py
ysfitsutilpy/fitting.py
ysfitsutilpy/hduutil.py
ysfitsutilpy/misc.py
ysfitsutilpy/preproc.py
ysfitsutilpy/imutil/__init__.py
ysfitsutilpy/imutil/docstrings.py
ysfitsutilpy/imutil/imarith.py
ysfitsutilpy/imutil/imcombine.py
ysfitsutilpy/imutil/imcopy.py
ysfitsutilpy/imutil/imsmooth.py
ysfitsutilpy/imutil/util_comb.py
ysfitsutilpy/imutil/util_lmedian.py
ysfitsutilpy/imutil/util_reject.py
ysfitsutilpy/tests/__init__.py
ysfitsutilpy/tests/test_misc.py
ysfitsutilpy-0.2.dist-info/LICENSE
ysfitsutilpy-0.2.dist-info/METADATA
ysfitsutilpy-0.2.dist-info/WHEEL
ysfitsutilpy-0.2.dist-info/top_level.txt
ysfitsutilpy-0.2.dist-info/RECORD
